README.md
setup.py
k8s_logger.egg-info/PKG-INFO
k8s_logger.egg-info/SOURCES.txt
k8s_logger.egg-info/dependency_links.txt
k8s_logger.egg-info/top_level.txt
logger/Config.py
logger/Logger.py
logger/__init__.py