Metadata-Version: 2.1
Name: k8s-logger
Version: 0.0.1
Summary: print model log to es
Home-page: UNKNOWN
Author: chunyu.piao
Author-email: chunyu.piao@bianlifeng.com
License: UNKNOWN
Platform: UNKNOWN
Classifier: Programming Language :: Python :: 3
Classifier: License :: OSI Approved :: MIT License
Classifier: Operating System :: OS Independent
